LICENSE
MANIFEST.in
README.rst
VERSION
requirements.txt
setup.py
unicore/__init__.py
unicore.comments.client.egg-info/PKG-INFO
unicore.comments.client.egg-info/SOURCES.txt
unicore.comments.client.egg-info/dependency_links.txt
unicore.comments.client.egg-info/namespace_packages.txt
unicore.comments.client.egg-info/not-zip-safe
unicore.comments.client.egg-info/requires.txt
unicore.comments.client.egg-info/top_level.txt
unicore/comments/__init__.py
unicore/comments/client/__init__.py
unicore/comments/client/base.py
unicore/comments/client/commentclient.py
unicore/comments/client/utils.py
unicore/comments/client/tests/__init__.py
unicore/comments/client/tests/fixtures.py
unicore/comments/client/tests/test_client.py
unicore/comments/client/tests/test_comment.py
unicore/comments/client/tests/test_commentpage.py