Metadata-Version: 1.1
Name: unicore.comments.client
Version: 0.1.2
Summary: Client library to interact with Universal Core's unicore.comments
Home-page: http://github.com/universalcore/unicore.comments.client
Author: Praekelt Foundation
Author-email: dev@praekelt.com
License: BSD
Keywords: authentication,user,universal,core
Platform: UNKNOWN
Classifier: Programming Language :: Python
Classifier: Topic :: Internet :: WWW/HTTP
Classifier: Topic :: Internet :: WWW/HTTP :: Dynamic Content
